finstock/__init__.py
finstock/client.py
finstock/models.py
finstock/utils.py
finstock-0.1.0.dist-info/METADATA
finstock-0.1.0.dist-info/WHEEL
finstock-0.1.0.dist-info/licenses/LICENSE
finstock-0.1.0.dist-info/RECORD
