Metadata-Version: 2.4
Name: finstock
Version: 0.1.0
Summary: 中国期货股票数据获取库 - 通过API获取K线数据并转换为pandas DataFrame
Project-URL: Homepage, https://github.com/finstock/finstock
Project-URL: Repository, https://github.com/finstock/finstock.git
Project-URL: Issues, https://github.com/finstock/finstock/issues
Project-URL: Documentation, https://finstock.readthedocs.io
Author-email: FinStock Team <contact@finstock.com>
License: MIT
License-File: LICENSE
Keywords: china,data,futures,kline,pandas,stocks,trading
Classifier: Development Status :: 4 - Beta
Classifier: Intended Audience :: Developers
Classifier: License :: OSI Approved :: MIT License
Classifier: Programming Language :: Python :: 3
Classifier: Programming Language :: Python :: 3.10
Classifier: Programming Language :: Python :: 3.11
Classifier: Programming Language :: Python :: 3.12
Classifier: Topic :: Office/Business :: Financial
Classifier: Topic :: Scientific/Engineering :: Information Analysis
Requires-Python: >=3.10
Requires-Dist: pandas>=2.3.3
Requires-Dist: pydantic>=2.5.0
Requires-Dist: requests>=2.32.5
Requires-Dist: typing-extensions>=4.8.0
Provides-Extra: dev
Requires-Dist: black>=23.0.0; extra == 'dev'
Requires-Dist: mypy>=1.7.0; extra == 'dev'
Requires-Dist: pytest-asyncio>=0.21.0; extra == 'dev'
Requires-Dist: pytest>=7.4.0; extra == 'dev'
Requires-Dist: ruff>=0.1.0; extra == 'dev'
